tests/analyzers/__init__.py
tests/analyzers/test_subgroup_error_analyzer.py
tests/custom_classes/__init__.py
tests/custom_classes/test_metrics_composer.py
tests/metrics/__init__.py
tests/preprocessing/__init__.py
tests/preprocessing/test_basic_preprocessing.py
tests/user_interfaces/__init__.py
tests/user_interfaces/conftest.py
tests/user_interfaces/test_compute_model_metrics.py
tests/user_interfaces/test_multiple_models_api.py
tests/utils/__init__.py
tests/utils/test_common_helpers.py
tests/utils/test_data_viz_utils.py
tests/utils/test_protected_groups_partitioning.py
tests/utils/test_stability_utils.py
virny/__init__.py
virny/__version__.py
virny/api.py
virny/analyzers/__init__.py
virny/analyzers/abstract_overall_variance_analyzer.py
virny/analyzers/abstract_subgroup_analyzer.py
virny/analyzers/batch_overall_variance_analyzer.py
virny/analyzers/batch_overall_variance_analyzer_postprocessing.py
virny/analyzers/subgroup_error_analyzer.py
virny/analyzers/subgroup_variance_analyzer.py
virny/analyzers/subgroup_variance_calculator.py
virny/configs/__init__.py
virny/configs/constants.py
virny/custom_classes/__init__.py
virny/custom_classes/base_dataset.py
virny/custom_classes/base_inprocessing_wrapper.py
virny/custom_classes/custom_logger.py
virny/custom_classes/metrics_composer.py
virny/custom_classes/metrics_interactive_visualizer.py
virny/custom_classes/metrics_visualizer.py
virny/custom_classes/wrappers/__init__.py
virny/custom_classes/wrappers/pytorch_tabular_wrapper.py
virny/datasets/__init__.py
virny/datasets/base.py
virny/datasets/compas.py
virny/datasets/education.py
virny/datasets/finance.py
virny/datasets/folktables.py
virny/datasets/healthcare.py
virny/datasets/data/COMPAS.csv
virny/datasets/data/bank-full.csv
virny/datasets/data/cardio.csv
virny/datasets/data/diabetes_dataset__2019.csv
virny/datasets/data/german_data_credit.csv
virny/datasets/data/law_school_clean.csv
virny/datasets/data/ricci_race.csv
virny/datasets/data/student_por_new.csv
virny-0.6.0.dist-info/LICENSE
virny-0.6.0.dist-info/METADATA
virny-0.6.0.dist-info/WHEEL
virny-0.6.0.dist-info/top_level.txt
virny-0.6.0.dist-info/RECORD
