Metadata-Version: 2.1
Name: virny
Version: 0.6.0
Summary: Python library for in-depth profiling of model performance across overall and disparity dimensions
Home-page: https://github.com/DataResponsibly/Virny
Author: Denys Herasymuk
Author-email: denis.gerasymuk799@gmail.com
License: BSD-3
Platform: UNKNOWN
Classifier: Intended Audience :: Science/Research
Classifier: Intended Audience :: Developers
Classifier: License :: OSI Approved :: BSD License
Classifier: Topic :: Software Development
Classifier: Topic :: Scientific/Engineering
Classifier: Programming Language :: Python
Classifier: Programming Language :: Python :: 3
Classifier: Programming Language :: Python :: 3.9
Classifier: Programming Language :: Python :: 3.10
Classifier: Programming Language :: Python :: 3.11
Classifier: Programming Language :: Python :: 3.12
Classifier: Operating System :: POSIX
Classifier: Operating System :: Unix
Classifier: Operating System :: MacOS
Requires-Python: >=3.9
License-File: LICENSE
Requires-Dist: setuptools>=74.1.0
Requires-Dist: aif360[reductions]>=0.6.1
Requires-Dist: matplotlib>=3.6.2
Requires-Dist: pandas>=1.5.2
Requires-Dist: altair>=4.2.0
Requires-Dist: scikit-learn>=1.2.0
Requires-Dist: tqdm>=4.64.1
Requires-Dist: gradio>=4.10.0
Requires-Dist: seaborn>=0.12.1
Requires-Dist: folktables>=0.0.11
Requires-Dist: munch>=2.5.0
Requires-Dist: PyYAML>=6.0
Requires-Dist: requests-toolbelt>=1.0.0
Requires-Dist: colorama>=0.4.6
Provides-Extra: dev
Requires-Dist: setuptools>=74.1.0; extra == "dev"
Requires-Dist: aif360[reductions]>=0.6.1; extra == "dev"
Requires-Dist: matplotlib>=3.6.2; extra == "dev"
Requires-Dist: pandas>=1.5.2; extra == "dev"
Requires-Dist: altair>=4.2.0; extra == "dev"
Requires-Dist: scikit-learn>=1.2.0; extra == "dev"
Requires-Dist: tqdm>=4.64.1; extra == "dev"
Requires-Dist: gradio>=4.10.0; extra == "dev"
Requires-Dist: seaborn>=0.12.1; extra == "dev"
Requires-Dist: folktables>=0.0.11; extra == "dev"
Requires-Dist: munch>=2.5.0; extra == "dev"
Requires-Dist: PyYAML>=6.0; extra == "dev"
Requires-Dist: requests-toolbelt>=1.0.0; extra == "dev"
Requires-Dist: colorama>=0.4.6; extra == "dev"
Requires-Dist: pytest~=7.2.1; extra == "dev"
Requires-Dist: aif360>=0.6.1; extra == "dev"
Requires-Dist: fairlearn>=0.9.0; extra == "dev"
Requires-Dist: xgboost>=1.7.2; extra == "dev"
Requires-Dist: python-dotenv>=1.0.0; extra == "dev"
Requires-Dist: pytorch-tabular>=1.1.0; extra == "dev"
Requires-Dist: pymongo==4.3.3; extra == "dev"
Provides-Extra: docs
Requires-Dist: scikit-learn; extra == "docs"
Requires-Dist: numpy; extra == "docs"
Requires-Dist: scipy; extra == "docs"
Requires-Dist: pandas; extra == "docs"
Requires-Dist: dominate; extra == "docs"
Requires-Dist: flask; extra == "docs"
Requires-Dist: ipykernel; extra == "docs"
Requires-Dist: jupyter-client; extra == "docs"
Requires-Dist: mike; extra == "docs"
Requires-Dist: mkdocs; extra == "docs"
Requires-Dist: mkdocs-awesome-pages-plugin; extra == "docs"
Requires-Dist: mkdocs-material; extra == "docs"
Requires-Dist: mkdocs-redirects; extra == "docs"
Requires-Dist: nbconvert; extra == "docs"
Requires-Dist: python-slugify; extra == "docs"
Requires-Dist: spacy; extra == "docs"
Provides-Extra: test
Requires-Dist: setuptools>=74.1.0; extra == "test"
Requires-Dist: aif360[reductions]>=0.6.1; extra == "test"
Requires-Dist: matplotlib>=3.6.2; extra == "test"
Requires-Dist: pandas>=1.5.2; extra == "test"
Requires-Dist: altair>=4.2.0; extra == "test"
Requires-Dist: scikit-learn>=1.2.0; extra == "test"
Requires-Dist: tqdm>=4.64.1; extra == "test"
Requires-Dist: gradio>=4.10.0; extra == "test"
Requires-Dist: seaborn>=0.12.1; extra == "test"
Requires-Dist: folktables>=0.0.11; extra == "test"
Requires-Dist: munch>=2.5.0; extra == "test"
Requires-Dist: PyYAML>=6.0; extra == "test"
Requires-Dist: requests-toolbelt>=1.0.0; extra == "test"
Requires-Dist: colorama>=0.4.6; extra == "test"
Requires-Dist: pytest~=7.2.1; extra == "test"
